cs233/Lab5/decoder.v
// mips_decode: a decoder for MIPS arithmetic instructions
//
// alu_op       (output) - control signal to be sent to the ALU
// writeenable  (output) - should a new value be captured by the register file
// rd_src       (output) - should the destination register be rd (0) or rt (1)
// alu_src2     (output) - should the 2nd ALU source be a register (0) or an immediate (1)
// except       (output) - set to 1 when we don't recognize an opdcode & funct combination
// control_type (output) - 00 = fallthrough, 01 = branch_target, 10 = jump_target, 11 = jump_register 
// mem_read     (output) - the register value written is coming from the memory
// word_we      (output) - we're writing a word's worth of data
// byte_we      (output) - we're only writing a byte's worth of data
// byte_load    (output) - we're doing a byte load
// slt          (output) - the instruction is an slt
// lui          (output) - the instruction is a lui
// addm         (output) - the instruction is an addm
// opcode        (input) - the opcode field from the instruction
// funct         (input) - the function field from the instruction
// zero          (input) - from the ALU
//

module mips_decode(alu_op, writeenable, rd_src, alu_src2, except, control_type,
                   mem_read, word_we, byte_we, byte_load, slt, lui, addm,
                   opcode, funct, zero);
    output [2:0] alu_op;
    output [1:0] alu_src2;
    output       writeenable, rd_src, except;
    output [1:0] control_type;
    output       mem_read, word_we, byte_we, byte_load, slt, lui, addm;
    input  [5:0] opcode, funct;
    input        zero;

    //set the types of op
    wire I_type = (opcode != 0);


    //set opcode funct to wires
    wire add =  (funct == `OP0_ADD) & (opcode == `OP_OTHER0);
    wire addu = (funct == `OP0_ADDU) & (opcode == `OP_OTHER0);
    wire sub = (funct == `OP0_SUB) & (opcode == `OP_OTHER0);
    wire and_ = (funct == `OP0_AND) & (opcode == `OP_OTHER0);
    wire or_ = (funct == `OP0_OR) & (opcode == `OP_OTHER0);
    wire nor_ = (funct == `OP0_NOR) & (opcode == `OP_OTHER0);
    wire xor_ = (funct == `OP0_XOR) & (opcode == `OP_OTHER0);
    wire jr = (funct == `OP0_JR) & (opcode == `OP_OTHER0);
    wire slt_ = (funct == `OP0_SLT) & (opcode == `OP_OTHER0);
     //addm wire
    wire addm = (funct == `OP0_ADDM) & (opcode ==  `OP_OTHER0); 

    //I type
    wire addi = (opcode == `OP_ADDI);
    wire addui = (opcode == `OP_ADDIU);
    wire and_i = (opcode == `OP_ANDI);
    wire or_i = (opcode == `OP_ORI);
    wire xor_i = (opcode == `OP_XORI);

    wire beq = (opcode == `OP_BEQ);
    wire bne = (opcode == `OP_BNE);
    wire lui_ = (opcode == `OP_LUI);
    wire lw = (opcode == `OP_LW);
    wire lbu = (opcode == `OP_LBU);
    wire sw = (opcode == `OP_SW);
    wire sb = (opcode == `OP_SB);

    //J type
    wire j = (opcode == `OP_J);

    /**
    * MARK: From lab 4 below
    **/
    //assign alu_src2
    assign alu_src2[0] = addi | addui | lw | lbu | sw | sb | addm;
    assign alu_src2[1] = and_i | or_i | xor_i | addm;

    //set alu_op
    assign alu_op[0] = sub | or_ | xor_ | or_i | xor_i | beq | bne | slt_;
    assign alu_op[1] = add | sub | nor_ | xor_ | addi | xor_i | beq | bne | slt_ | lw | lbu | sw | sb | addm;
    assign alu_op[2] = and_ | or_ | nor_ | xor_ | and_i | or_i | xor_i;

    //set control_type
    assign control_type[0] = ((beq & zero) | (bne & !zero) | jr);
    assign control_type[1] = (j | jr); 

    //set the rd_src
    assign rd_src = addi | addui | and_i | or_i | xor_i | lui_ | lw | lbu; 

    //memrd wordwe
    assign mem_read = lw | lbu | addm;
    assign word_we = sw;
    assign byte_we = sb;
    assign byte_load = lbu;
    assign lui = lui_;
    assign slt = slt_;
    
    assign writeenable = add | addu | sub | and_ | or_ | nor_ | xor_ | addi | addui | and_i | or_i | xor_i | lui_ | slt_ | lw | lbu | addm;
    assign except = ~(add | addu | sub | and_ | or_ | nor_ | xor_ | addi | addui | and_i | or_i | xor_i | beq | bne | j | jr | lui_ | slt_ | lw | lbu | sw | sb | addm);



endmodule // mips_decode

cs233/Lab5/decoder_tb.v
module decoder_test;
    reg [5:0] opcode, funct;
    reg       zero  = 0;

    initial begin
        $dumpfile("decoder.vcd");
        $dumpvars(0, decoder_test);

        // remember that all your instructions from last week should still work
             opcode = `OP_OTHER0; funct = `OP0_ADD; // see if addition still works
        # 10 opcode = `OP_OTHER0; funct = `OP0_SUB; // see if subtraction still works
        // test all of the others here
        
        // as should all the new instructions from this week
        # 10 opcode = `OP_BEQ; zero = 0; // try a not taken beq
        # 10 opcode = `OP_BEQ; zero = 1; // try a taken beq
        // add more tests here!
        # 10 opcode = `OP_J;
        # 10 opcode = `OP_OTHER0; funct = `OP0_JR;
        # 10 opcode = `OP_OTHER0; funct = `OP0_SLT;
        # 10 opcode = `OP_LW;
        # 10 opcode = `OP_LBU;
        # 10 opcode = `OP_SW;
        # 10 opcode = `OP_SB;
        # 10 opcode = `OP0_ADDM;
        # 10 opcode = `OP_BNE;
        # 10 $finish;
    end

    // use gtkwave to test correctness
    wire [2:0] alu_op;
    wire [1:0] alu_src2;
    wire       writeenable, rd_src, except;
    wire [1:0] control_type;
    wire       mem_read, word_we, byte_we, byte_load, slt, lui, addm;
    mips_decode decoder(alu_op, writeenable, rd_src, alu_src2, except, control_type,
                        mem_read, word_we, byte_we, byte_load, slt, lui, addm,
                        opcode, funct, zero);
endmodule // decoder_test

cs233/Lab5/decoder.vcd
$date
	Thu Feb 20 19:39:54 2020
$end
$version
	Icarus Verilog
$end
$timescale
	1s
$end
$scope module decoder_test $end
$var wire 1 ! writeenable $end
$var wire 1 " word_we $end
$var wire 1 # slt $end
$var wire 1 $ rd_src $end
$var wire 1 % mem_read $end
$var wire 1 & lui $end
$var wire 1 ' except $end
$var wire 2 ( control_type [1:0] $end
$var wire 1 ) byte_we $end
$var wire 1 * byte_load $end
$var wire 2 + alu_src2 [1:0] $end
$var wire 3 , alu_op [2:0] $end
$var wire 1 - addm $end
$var reg 6 . funct [5:0] $end
$var reg 6 / opcode [5:0] $end
$var reg 1 0 zero $end
$scope module decoder $end
$var wire 1 1 add $end
$var wire 1 2 addu $end
$var wire 1 3 and_ $end
$var wire 1 * byte_load $end
$var wire 1 ) byte_we $end
$var wire 1 ' except $end
$var wire 6 4 funct [5:0] $end
$var wire 1 5 jr $end
$var wire 1 & lui $end
$var wire 1 % mem_read $end
$var wire 1 6 nor_ $end
$var wire 6 7 opcode [5:0] $end
$var wire 1 8 or_ $end
$var wire 1 $ rd_src $end
$var wire 1 # slt $end
$var wire 1 9 slt_ $end
$var wire 1 : sub $end
$var wire 1 " word_we $end
$var wire 1 ! writeenable $end
$var wire 1 ; xor_ $end
$var wire 1 0 zero $end
$var wire 1 < xor_i $end
$var wire 1 = sw $end
$var wire 1 > sb $end
$var wire 1 ? or_i $end
$var wire 1 @ lw $end
$var wire 1 A lui_ $end
$var wire 1 B lbu $end
$var wire 1 C j $end
$var wire 2 D control_type [1:0] $end
$var wire 1 E bne $end
$var wire 1 F beq $end
$var wire 1 G and_i $end
$var wire 2 H alu_src2 [1:0] $end
$var wire 3 I alu_op [2:0] $end
$var wire 1 J addui $end
$var wire 1 - addm $end
$var wire 1 K addi $end
$var wire 1 L I_type $end
$upscope $end
$upscope $end
$enddefinitions $end
#0
$dumpvars
0L
0K
0J
b10 I
b0 H
0G
0F
0E
b0 D
0C
0B
0A
0@
0?
0>
0=
0<
0;
0:
09
08
b0 7
06
05
b100000 4
03
02
11
00
b0 /
b100000 .
0-
b10 ,
b0 +
0*
0)
b0 (
0'
0&
0%
0$
0#
0"
1!
$end
#10
b11 ,
b11 I
01
1:
b100010 .
b100010 4
#20
0!
0:
1L
1F
b100 /
b100 7
#30
b1 (
b1 D
10
#40
b0 ,
b0 I
b10 (
b10 D
0F
1C
b10 /
b10 7
#50
15
b11 (
b11 D
b1000 .
b1000 4
0L
0C
b0 /
b0 7
#60
1!
b0 (
b0 D
b11 ,
b11 I
05
1#
19
b101010 .
b101010 4
#70
b1 +
b1 H
b10 ,
b10 I
1%
1$
0#
09
1L
1@
b100011 /
b100011 7
#80
0@
1*
1B
b100100 /
b100100 7
#90
0!
0%
0$
0*
0B
1"
1=
b101011 /
b101011 7
#100
0"
0=
1)
1>
b101000 /
b101000 7
#110
b0 +
b0 H
1!
1%
0)
0>
1-
b101100 /
b101100 7
#120
0'
0!
0%
b11 ,
b11 I
1E
0-
b101 /
b101 7
