cs233/Lab2/mux.v
// output is A (when control == 0) or B (when control == 1)
module mux2(out, A, B, control);
    output out;
    input  A, B;
    input  control;
    wire   wA, wB, not_control;

    not n1(not_control, control);
    and a1(wA, A, not_control);
    and a2(wB, B, control);
    or  o1(out, wA, wB);

endmodule // mux2


// output is A (when control == 00) or B (when control == 01) or
//           C (when control == 10) or D (when control == 11)
module mux4(out, A, B, C, D, control);
    output      out;
    input       A, B, C, D;
    input [1:0] control;
    wire double_not, not_control0, not_control1, wA, not_0, not_1, wB, wC, double_yes, wD, out_1, out_2;

    not n1(not_control0, control[0]);
    not n2(not_control1, control[1]);

    and a1(double_not, not_control0, not_control1);
    and a2(wA, A, double_not);
    and a3(not_0, not_control0, control[1]);
    and a4(not_1, not_control1, control[0]);
    and a5(wB, B, not_1);
    and a6(wC, C, not_0);
    and a7(double_yes, control[0], control[1]);
    and a8(wD, D, double_yes);
    or o1(out_1, wA, wB);
    or o2(out_2, out_1, wC);
    or o3(out, out_2, wD);



endmodule // mux4

cs233/Lab2/logicunit.v
// 00 -> AND, 01 -> OR, 10 -> NOR, 11 -> XOR
module logicunit(out, A, B, control);
    output      out;
    input       A, B;
    input [1:0] control;
    wire w_and, w_or, w_nor, w_xor;
    
    and a1(w_and, A, B);
    or o1(w_or, A, B);
    nor n1(w_nor, A, B);
    xor x1(w_xor, A, B);

    mux4 m1(out, w_and, w_or, w_nor, w_xor, control);
    
endmodule // logicunit

cs233/Lab2/alu1.v
module full_adder(sum, cout, a, b, cin);
    output sum, cout;
    input  a, b, cin;
    wire   partial_s, partial_c1, partial_c2;

    xor x0(partial_s, a, b);
    xor x1(sum, partial_s, cin);
    and a0(partial_c1, a, b);
    and a1(partial_c2, partial_s, cin);
    or  o1(cout, partial_c1, partial_c2);
endmodule // full_adder

`define ALU_UADD   3'h0
`define ALU_ADD    3'h2
`define ALU_SUB    3'h3
`define ALU_AND    3'h4
`define ALU_OR     3'h5
`define ALU_NOR    3'h6
`define ALU_XOR    3'h7

// 0xx -> arithmetic, 1xx -> logic
module alu1(out, carryout, A, B, carryin, control);
    output      out, carryout;
    input       A, B, carryin;
    input [2:0] control;

    wire sum, logic_out, B_b;

    xor x1(B_b, B, control[0]);
    full_adder add1(sum, carryout, A, B_b, carryin);
    logicunit lg1(logic_out, A, B, control[1:0]);

    mux2 m2(out, sum, logic_out, control[2]);


    // add code here!!!

endmodule // alu1

cs233/Lab2/alu1_tb.v
module alu1_test;
    // exhaustively test your 1-bit ALU implementation by adapting mux4_tb.v
    reg A = 0;
    always #1 A = !A;
    reg B = 0;
    always #2 B = !B;
    reg carryin = 0;
    always #4 carryin = !carryin;
     
    reg [2:0] control = 0;
     
    initial begin
        $dumpfile("alu1.vcd");
        $dumpvars(0, alu1_test);

        // control is initially 0
        # 8 control = 1; // wait 16 time units (why 16?) and then set it to 1
        # 8 control = 2; // wait 16 time units and then set it to 2
        # 8 control = 3; // wait 16 time units and then set it to 3
        # 8 control = 4; // wait 16 time units (why 16?) and then set it to 1
        # 8 control = 5; // wait 16 time units and then set it to 2
        # 8 control = 6; // wait 16 time units and then set it to 3# 16 control = 1; // wait 16 time units (why 16?) and then set it to 1
        # 8 control = 7; // wait 16 time units and then set it to 2
        # 8 $finish; // wait 16 time units and then end the simulation
    end

    wire out, carryout;
    alu1 m4(out, carryout, A, B, carryin, control);

// exhaustively test your logic unit implementation by adapting mux4_tb.v
endmodule

cs233/Lab2/alu1.vcd
$date
	Mon Feb  3 21:47:39 2020
$end
$version
	Icarus Verilog
$end
$timescale
	1s
$end
$scope module alu1_test $end
$var wire 1 ! out $end
$var wire 1 " carryout $end
$var reg 1 # A $end
$var reg 1 $ B $end
$var reg 1 % carryin $end
$var reg 3 & control [2:0] $end
$scope module m4 $end
$var wire 1 # A $end
$var wire 1 $ B $end
$var wire 1 ' B_b $end
$var wire 1 % carryin $end
$var wire 3 ( control [2:0] $end
$var wire 1 ) sum $end
$var wire 1 ! out $end
$var wire 1 * logic_out $end
$var wire 1 " carryout $end
$scope module add1 $end
$var wire 1 # a $end
$var wire 1 ' b $end
$var wire 1 % cin $end
$var wire 1 " cout $end
$var wire 1 + partial_c1 $end
$var wire 1 , partial_c2 $end
$var wire 1 - partial_s $end
$var wire 1 ) sum $end
$upscope $end
$scope module lg1 $end
$var wire 1 # A $end
$var wire 1 $ B $end
$var wire 2 . control [1:0] $end
$var wire 1 / w_and $end
$var wire 1 0 w_nor $end
$var wire 1 1 w_or $end
$var wire 1 2 w_xor $end
$var wire 1 * out $end
$scope module m1 $end
$var wire 1 / A $end
$var wire 1 1 B $end
$var wire 1 0 C $end
$var wire 1 2 D $end
$var wire 2 3 control [1:0] $end
$var wire 1 4 double_not $end
$var wire 1 5 double_yes $end
$var wire 1 6 not_0 $end
$var wire 1 7 not_1 $end
$var wire 1 8 not_control0 $end
$var wire 1 9 not_control1 $end
$var wire 1 * out $end
$var wire 1 : out_1 $end
$var wire 1 ; out_2 $end
$var wire 1 < wA $end
$var wire 1 = wB $end
$var wire 1 > wC $end
$var wire 1 ? wD $end
$upscope $end
$upscope $end
$scope module m2 $end
$var wire 1 ) A $end
$var wire 1 * B $end
$var wire 1 @ control $end
$var wire 1 A not_control $end
$var wire 1 ! out $end
$var wire 1 B wA $end
$var wire 1 C wB $end
$upscope $end
$upscope $end
$upscope $end
$enddefinitions $end
#0
$dumpvars
0C
0B
1A
0@
0?
0>
0=
0<
0;
0:
19
18
07
06
05
14
b0 3
02
01
10
0/
b0 .
0-
0,
0+
0*
0)
b0 (
0'
b0 &
0%
0$
0#
0"
0!
$end
#1
1!
1B
1)
1-
11
00
12
1#
#2
1'
0#
1$
#3
1*
0!
1;
0B
1:
0)
1"
1<
0-
1+
1/
02
1#
#4
0*
0;
0:
1!
0"
0<
1B
0+
0'
0/
01
10
1)
0#
0$
1%
#5
0!
0B
1"
0)
1,
1-
11
00
12
1#
#6
1'
0#
1$
#7
1*
1!
1;
1B
1:
1)
0,
1<
0-
1+
1/
02
1#
#8
0*
0;
04
0:
1!
08
17
0"
0<
1B
1-
0+
0/
01
10
1)
b1 .
b1 3
0#
0$
0%
b1 &
b1 (
#9
1*
0!
1;
0B
1:
0)
1"
1=
0-
1+
11
00
12
1#
#10
0"
0+
0'
0#
1$
#11
1!
1B
1)
1-
1/
02
1#
#12
0*
0;
0:
0!
0=
0B
1"
1'
0/
01
10
0)
1,
0#
0$
1%
#13
1*
1!
1;
1B
1:
1)
0,
1=
0-
1+
11
00
12
1#
#14
0"
0+
0'
0#
1$
#15
0!
0B
1"
0)
1,
1-
1/
02
1#
#16
1*
1>
1;
16
0:
0!
18
09
07
0=
0B
0"
0-
0/
01
10
0)
0,
b10 .
b10 3
0#
0$
0%
b10 &
b10 (
#17
1!
0*
1B
0;
1)
0>
1-
11
00
12
1#
#18
1'
0#
1$
#19
0!
0B
0)
1"
0-
1+
1/
02
1#
#20
1*
1;
1!
0"
1>
1B
0+
0'
0/
01
10
1)
0#
0$
1%
#21
0!
0*
0B
1"
0;
0)
1,
0>
1-
11
00
12
1#
#22
1'
0#
1$
#23
1!
1B
1)
0,
0-
1+
1/
02
1#
#24
0*
06
0;
1!
08
15
0"
0>
1B
1-
0+
0/
01
10
1)
b11 .
b11 3
0#
0$
0%
b11 &
b11 (
#25
0!
0B
1*
0)
1"
1?
0-
1+
11
00
12
1#
#26
0"
0+
0'
0#
1$
#27
1!
1B
0*
1)
0?
1-
1/
02
1#
#28
0!
0B
1"
1'
0/
01
10
0)
1,
0#
0$
1%
#29
1!
1B
1*
1)
0,
1?
0-
1+
11
00
12
1#
#30
0"
0+
0'
0#
1$
#31
0!
0B
1"
0*
0)
1,
0?
1-
1/
02
1#
#32
14
18
19
05
0"
0A
0-
0/
01
10
0)
0,
b0 .
b0 3
1@
0#
0$
0%
b100 &
b100 (
#33
1)
1-
11
00
12
1#
#34
1'
0#
1$
#35
1!
1C
1*
1;
1:
0)
1"
1<
0-
1+
1/
02
1#
#36
0!
0C
0*
0;
0:
0"
0<
0+
0'
0/
01
10
1)
0#
0$
1%
#37
1"
0)
1,
1-
11
00
12
1#
#38
1'
0#
1$
#39
1!
1C
1*
1;
1:
1)
0,
1<
0-
1+
1/
02
1#
#40
0!
0C
0*
0;
04
0:
08
17
0"
0<
1-
0+
0/
01
10
1)
b1 .
b1 3
0#
0$
0%
b101 &
b101 (
#41
1!
1C
1*
1;
1:
0)
1"
1=
0-
1+
11
00
12
1#
#42
0"
0+
0'
0#
1$
#43
1)
1-
1/
02
1#
#44
0!
0C
0*
0;
0:
0=
1"
1'
0/
01
10
0)
1,
0#
0$
1%
#45
1!
1C
1*
1;
1:
1)
0,
1=
0-
1+
11
00
12
1#
#46
0"
0+
0'
0#
1$
#47
1"
0)
1,
1-
1/
02
1#
#48
1!
1C
1*
1>
1;
16
0:
18
09
07
0=
0"
0-
0/
01
10
0)
0,
b10 .
b10 3
0#
0$
0%
b110 &
b110 (
#49
0!
0C
0*
0;
1)
0>
1-
11
00
12
1#
#50
1'
0#
1$
#51
0)
1"
0-
1+
1/
02
1#
#52
1!
1C
1*
1;
0"
1>
0+
0'
0/
01
10
1)
0#
0$
1%
#53
0!
0C
0*
1"
0;
0)
1,
0>
1-
11
00
12
1#
#54
1'
0#
1$
#55
1)
0,
0-
1+
1/
02
1#
#56
0!
0C
0*
06
0;
08
15
0"
0>
1-
0+
0/
01
10
1)
b11 .
b11 3
0#
0$
0%
b111 &
b111 (
#57
1!
1C
1*
0)
1"
1?
0-
1+
11
00
12
1#
#58
0"
0+
0'
0#
1$
#59
0!
0C
0*
1)
0?
1-
1/
02
1#
#60
1"
1'
0/
01
10
0)
1,
0#
0$
1%
#61
1!
1C
1*
1)
0,
1?
0-
1+
11
00
12
1#
#62
0"
0+
0'
0#
1$
#63
0!
0C
1"
0*
0)
1,
0?
1-
1/
02
1#
#64
0"
1'
0/
01
10
1)
0,
0#
0$
0%
