cs233/Lab2/mux.v
// output is A (when control == 0) or B (when control == 1)
module mux2(out, A, B, control);
    output out;
    input  A, B;
    input  control;
    wire   wA, wB, not_control;

    not n1(not_control, control);
    and a1(wA, A, not_control);
    and a2(wB, B, control);
    or  o1(out, wA, wB);

endmodule // mux2


// output is A (when control == 00) or B (when control == 01) or
//           C (when control == 10) or D (when control == 11)
module mux4(out, A, B, C, D, control);
    output      out;
    input       A, B, C, D;
    input [1:0] control;
    wire double_not, not_control0, not_control1, wA, not_0, not_1, wB, wC, double_yes, wD, out_1, out_2;

    not n1(not_control0, control[0]);
    not n2(not_control1, control[1]);

    and a1(double_not, not_control0, not_control1);
    and a2(wA, A, double_not);
    and a3(not_0, not_control0, control[1]);
    and a4(not_1, not_control1, control[0]);
    and a5(wB, B, not_1);
    and a6(wC, C, not_0);
    and a7(double_yes, control[0], control[1]);
    and a8(wD, D, double_yes);
    or o1(out_1, wA, wB);
    or o2(out_2, out_1, wC);
    or o3(out, out_2, wD);



endmodule // mux4

cs233/Lab2/logicunit.v
// 00 -> AND, 01 -> OR, 10 -> NOR, 11 -> XOR
module logicunit(out, A, B, control);
    output      out;
    input       A, B;
    input [1:0] control;
    wire w_and, w_or, w_nor, w_xor;
    
    and a1(w_and, A, B);
    or o1(w_or, A, B);
    nor n1(w_nor, A, B);
    xor x1(w_xor, A, B);

    mux4 m1(out, w_and, w_or, w_nor, w_xor, control);
    
endmodule // logicunit

cs233/Lab2/logicunit_tb.v
module logicunit_test;

    // cycle through all combinations of A, B, C, D every 16 time units
    reg A = 0;
    always #1 A = !A;
    reg B = 0;
    always #2 B = !B;
     
    reg [1:0] control = 0;
     
    initial begin
        $dumpfile("logicunit.vcd");
        $dumpvars(0, logicunit_test);

        // control is initially 0
        # 16 control = 1; // wait 16 time units (why 16?) and then set it to 1
        # 16 control = 2; // wait 16 time units and then set it to 2
        # 16 control = 3; // wait 16 time units and then set it to 3
        # 16 $finish; // wait 16 time units and then end the simulation
    end

    wire out;
    logicunit m4(out, A, B, control);

    // you really should be using gtkwave instead
    /*
    initial begin
        $display("A B s o");
        $monitor("%d %d %d %d %d %d (at time %t)", A, B, control, out, $time);
    end
    */
// exhaustively test your logic unit implementation by adapting mux4_tb.v
endmodule // logicunit_test

cs233/Lab2/logicunit.vcd
$date
	Mon Feb  3 21:47:39 2020
$end
$version
	Icarus Verilog
$end
$timescale
	1s
$end
$scope module logicunit_test $end
$var wire 1 ! out $end
$var reg 1 " A $end
$var reg 1 # B $end
$var reg 2 $ control [1:0] $end
$scope module m4 $end
$var wire 1 " A $end
$var wire 1 # B $end
$var wire 2 % control [1:0] $end
$var wire 1 & w_and $end
$var wire 1 ' w_nor $end
$var wire 1 ( w_or $end
$var wire 1 ) w_xor $end
$var wire 1 ! out $end
$scope module m1 $end
$var wire 1 & A $end
$var wire 1 ( B $end
$var wire 1 ' C $end
$var wire 1 ) D $end
$var wire 2 * control [1:0] $end
$var wire 1 + double_not $end
$var wire 1 , double_yes $end
$var wire 1 - not_0 $end
$var wire 1 . not_1 $end
$var wire 1 / not_control0 $end
$var wire 1 0 not_control1 $end
$var wire 1 ! out $end
$var wire 1 1 out_1 $end
$var wire 1 2 out_2 $end
$var wire 1 3 wA $end
$var wire 1 4 wB $end
$var wire 1 5 wC $end
$var wire 1 6 wD $end
$upscope $end
$upscope $end
$upscope $end
$enddefinitions $end
#0
$dumpvars
06
05
04
03
02
01
10
1/
0.
0-
0,
1+
b0 *
0)
0(
1'
0&
b0 %
b0 $
0#
0"
0!
$end
#1
1(
0'
1)
1"
#2
0"
1#
#3
1!
12
11
13
1&
0)
1"
#4
0!
02
01
03
0&
0(
1'
0"
0#
#5
1(
0'
1)
1"
#6
0"
1#
#7
1!
12
11
13
1&
0)
1"
#8
0!
02
01
03
0&
0(
1'
0"
0#
#9
1(
0'
1)
1"
#10
0"
1#
#11
1!
12
11
13
1&
0)
1"
#12
0!
02
01
03
0&
0(
1'
0"
0#
#13
1(
0'
1)
1"
#14
0"
1#
#15
1!
12
11
13
1&
0)
1"
#16
0!
02
01
0+
03
0/
1.
0&
0(
1'
0"
0#
b1 $
b1 %
b1 *
#17
1!
12
11
14
1(
0'
1)
1"
#18
0"
1#
#19
1&
0)
1"
#20
0!
02
01
04
0&
0(
1'
0"
0#
#21
1!
12
11
14
1(
0'
1)
1"
#22
0"
1#
#23
1&
0)
1"
#24
0!
02
01
04
0&
0(
1'
0"
0#
#25
1!
12
11
14
1(
0'
1)
1"
#26
0"
1#
#27
1&
0)
1"
#28
0!
02
01
04
0&
0(
1'
0"
0#
#29
1!
12
11
14
1(
0'
1)
1"
#30
0"
1#
#31
1&
0)
1"
#32
15
01
1-
04
1/
00
0.
0&
0(
1'
0"
0#
b10 $
b10 %
b10 *
#33
0!
02
05
1(
0'
1)
1"
#34
0"
1#
#35
1&
0)
1"
#36
1!
12
15
0&
0(
1'
0"
0#
#37
0!
02
05
1(
0'
1)
1"
#38
0"
1#
#39
1&
0)
1"
#40
1!
12
15
0&
0(
1'
0"
0#
#41
0!
02
05
1(
0'
1)
1"
#42
0"
1#
#43
1&
0)
1"
#44
1!
12
15
0&
0(
1'
0"
0#
#45
0!
02
05
1(
0'
1)
1"
#46
0"
1#
#47
1&
0)
1"
#48
0!
02
0-
05
0/
1,
0&
0(
1'
0"
0#
b11 $
b11 %
b11 *
#49
1!
16
1(
0'
1)
1"
#50
0"
1#
#51
0!
06
1&
0)
1"
#52
0&
0(
1'
0"
0#
#53
1!
16
1(
0'
1)
1"
#54
0"
1#
#55
0!
06
1&
0)
1"
#56
0&
0(
1'
0"
0#
#57
1!
16
1(
0'
1)
1"
#58
0"
1#
#59
0!
06
1&
0)
1"
#60
0&
0(
1'
0"
0#
#61
1!
16
1(
0'
1)
1"
#62
0"
1#
#63
0!
06
1&
0)
1"
#64
0&
0(
1'
0"
0#
