cs233/pl lab1/blackbox1.v
module blackbox(n, j, k, d);
    output n;
    input  j, k, d;
    wire   w01, w05, w06, w08, w15, w17, w22, w23, w28, w29, w38, w45, w49, w50, w63, w64, w66, w72, w81, w83;
    or  o59(n, w28, w06, w64);
    and a42(w28, w05, w01, w38);
    not n71(w38, w49);
    and a68(w06, w01, w49, w05);
    and a67(w64, w29, w63);
    not n62(w29, w01);
    or  o95(w63, w72, w22);
    and a97(w72, w05, w49);
    and a51(w22, w83, w05);
    not n88(w83, w49);
    and a57(w01, k, w50);
    or  o10(w50, j, w15);
    and a78(w15, d, w45);
    not n77(w45, j);
    and a53(w49, k, w17);
    or  o73(w17, w23, w66);
    not n9(w23, d);
    not n41(w66, j);
    or  o33(w05, w81, j, w08);
    not n91(w81, k);
    not n96(w08, d);
endmodule // blackbox

cs233/pl lab1/blackbox_tb.v
module bb1_test;
    reg w, v, j;                           // these are inputs to "circuit under test"
                                              // use "reg" not "wire" so can assign a value
    wire c;                        // wires for the outputs of "circuit under test"

    blackbox bb1(c, w, v, j);  // the circuit under test

    initial begin                             // initial = run at beginning of simulation
                                              // begin/end = associate block with initial

        $dumpfile("bb1.vcd");                  // name of dump file to create
        $dumpvars(0,bb1_test);                 // record all signals of module "sc_test" and sub-modules
                                              // remember to change "sc_test" to the correct
                                              // module name when writing your own test benches

        // test all four input combinations
        // remember that 2 inputs means 2^2 = 4 combinations
        // 3 inputs would mean 2^3 = 8 combinations to test, and so on
        // this is very similar to the input columns of a truth table
        w = 0; v = 0; j = 0; # 10;             // set initial values and wait 10 time units
        w = 0; v = 0; j = 1; # 10;             // change inputs and then wait 10 time units
        w = 0; v = 1; j = 0; # 10;             // as above
        w = 0; v = 1; j = 1; # 10;
        w = 1; v = 0; j = 0; # 10;
        w = 1; v = 0; j = 1; # 10;
        w = 1; v = 1; j = 0; # 10;
        w = 1; v = 1; j = 1; # 10;

        $finish;                              // end the simulation
    end

    initial
        $monitor("At time %2t, w = %d v = %d j = %d c = %d",
                 $time, w, v, j, c);
endmodule // sc2_test

cs233/pl lab1/bb1.vcd
$date
	Sun Jan 26 22:22:28 2020
$end
$version
	Icarus Verilog
$end
$timescale
	1s
$end
$scope module bb1_test $end
$var wire 1 ! c $end
$var reg 1 " j $end
$var reg 1 # v $end
$var reg 1 $ w $end
$scope module bb1 $end
$var wire 1 " d $end
$var wire 1 $ j $end
$var wire 1 # k $end
$var wire 1 ! n $end
$var wire 1 % w01 $end
$var wire 1 & w05 $end
$var wire 1 ' w06 $end
$var wire 1 ( w08 $end
$var wire 1 ) w15 $end
$var wire 1 * w17 $end
$var wire 1 + w22 $end
$var wire 1 , w23 $end
$var wire 1 - w28 $end
$var wire 1 . w29 $end
$var wire 1 / w38 $end
$var wire 1 0 w45 $end
$var wire 1 1 w49 $end
$var wire 1 2 w50 $end
$var wire 1 3 w63 $end
$var wire 1 4 w64 $end
$var wire 1 5 w66 $end
$var wire 1 6 w72 $end
$var wire 1 7 w81 $end
$var wire 1 8 w83 $end
$upscope $end
$upscope $end
$enddefinitions $end
#0
$dumpvars
18
17
06
15
14
13
02
01
10
1/
1.
0-
1,
1+
1*
0)
1(
0'
1&
0%
0$
0#
0"
1!
$end
#10
12
1)
0,
0(
1"
#20
1!
14
0+
02
1.
08
16
0'
0/
0)
1,
1(
0%
11
07
0"
1#
#30
0!
04
0.
03
1%
06
12
0&
1)
0,
0(
1"
#40
1!
14
13
1+
1.
18
1/
0)
1,
1(
0%
01
17
00
05
1&
0"
0#
1$
#50
0*
0,
0(
1"
#60
0+
08
16
1'
0/
11
04
1*
0.
0-
1,
1(
1%
07
0"
1#
#70
1+
13
1-
18
06
0'
1/
01
0*
0,
0(
1"
